[{"info": "{\"mmsi\":\"227503000\",\"vesselType\":\"purse_seine\",\"search\":\"Yes\",\"search_url\":\"http://www.fao.org/figis/vrmf/finder/IOTC/!/display/vessel/UID/000001461#.Vs5s3fkrLIU\"}", "user_id": 10, "links": ["<link rel='parent' title='project' href='http://crowd.globalfishingwatch.org/api/project/2'/>", "<link rel='parent' title='task' href='http://crowd.globalfishingwatch.org/api/task/4059'/>"], "task_id": 4059, "created": "2016-02-25T02:37:14.543478", "finish_time": "2016-02-25T02:54:59.613013", "calibration": null, "user_ip": null, "link": "<link rel='self' title='taskrun' href='http://crowd.globalfishingwatch.org/api/taskrun/2370'/>", "timeout": null, "project_id": 2, "id": 2370}, {"info": "{\"mmsi\":\"227503000\",\"vesselType\":\"purse_seine\",\"search\":\"Yes\",\"search_url\":\"http://ec.europa.eu/fisheries/fleet/index.cfm?method=Search.DetailSearchSimple&event_key=28297041&search_type=advanced&search_id=5514\"}", "user_id": 12, "links": ["<link rel='parent' title='project' href='http://crowd.globalfishingwatch.org/api/project/2'/>", "<link rel='parent' title='task' href='http://crowd.globalfishingwatch.org/api/task/4059'/>"], "task_id": 4059, "created": "2016-02-27T19:02:20.482648", "finish_time": "2016-02-27T19:11:49.736332", "calibration": null, "user_ip": null, "link": "<link rel='self' title='taskrun' href='http://crowd.globalfishingwatch.org/api/taskrun/2447'/>", "timeout": null, "project_id": 2, "id": 2447}, {"info": "{\"mmsi\":\"227503000\",\"vesselType\":\"purse_seine\",\"search\":\"Yes\",\"search_url\":\"http://www.fao.org/figis/vrmf/finder/!/display/vessel/UID/013015726/#.VtMvF_IrLIU\"}", "user_id": 19, "links": ["<link rel='parent' title='project' href='http://crowd.globalfishingwatch.org/api/project/2'/>", "<link rel='parent' title='task' href='http://crowd.globalfishingwatch.org/api/task/4059'/>"], "task_id": 4059, "created": "2016-02-28T17:26:33.321543", "finish_time": "2016-02-28T17:32:27.149701", "calibration": null, "user_ip": null, "link": "<link rel='self' title='taskrun' href='http://crowd.globalfishingwatch.org/api/taskrun/2454'/>", "timeout": null, "project_id": 2, "id": 2454}, {"info": "{\"mmsi\":\"227503000\",\"vesselType\":\"purse_seine\",\"search\":\"Yes\",\"search_url\":\"http://ec.europa.eu/fisheries/fleet/index.cfm?method=Search.DetailSearchSimple&event_key=28297041&search_type=advanced&search_id=896\"}", "user_id": 9, "links": ["<link rel='parent' title='project' href='http://crowd.globalfishingwatch.org/api/project/2'/>", "<link rel='parent' title='task' href='http://crowd.globalfishingwatch.org/api/task/4059'/>"], "task_id": 4059, "created": "2016-02-29T19:11:06.253272", "finish_time": "2016-02-29T19:13:57.183860", "calibration": null, "user_ip": null, "link": "<link rel='self' title='taskrun' href='http://crowd.globalfishingwatch.org/api/taskrun/2461'/>", "timeout": null, "project_id": 2, "id": 2461}, {"info": "{\"mmsi\":\"227503000\",\"vesselType\":\"purse_seine\",\"search\":\"Yes\",\"search_url\":\"http://ec.europa.eu/fisheries/fleet/index.cfm?method=Search.DetailSearchSimple&event_key=28297041&search_type=simple&search_id=8222\"}", "user_id": 14, "links": ["<link rel='parent' title='project' href='http://crowd.globalfishingwatch.org/api/project/2'/>", "<link rel='parent' title='task' href='http://crowd.globalfishingwatch.org/api/task/4059'/>"], "task_id": 4059, "created": "2016-03-01T14:57:04.392031", "finish_time": "2016-03-01T14:58:53.537921", "calibration": null, "user_ip": null, "link": "<link rel='self' title='taskrun' href='http://crowd.globalfishingwatch.org/api/taskrun/2478'/>", "timeout": null, "project_id": 2, "id": 2478}, {"info": "{\"mmsi\":\"227503000\",\"vesselType\":\"purse_seine\",\"search\":\"No\",\"search_url\":\"\"}", "user_id": 20, "links": ["<link rel='parent' title='project' href='http://crowd.globalfishingwatch.org/api/project/2'/>", "<link rel='parent' title='task' href='http://crowd.globalfishingwatch.org/api/task/4059'/>"], "task_id": 4059, "created": "2016-03-02T18:51:05.818831", "finish_time": "2016-03-02T18:53:22.944476", "calibration": null, "user_ip": null, "link": "<link rel='self' title='taskrun' href='http://crowd.globalfishingwatch.org/api/taskrun/2543'/>", "timeout": null, "project_id": 2, "id": 2543}, {"info": "{\"mmsi\":\"227503000\",\"vesselType\":\"purse_seine\",\"search\":\"Yes\",\"search_url\":\"http://www.bateaux-fecamp.fr/jean-marie-christian-3/\"}", "user_id": 18, "links": ["<link rel='parent' title='project' href='http://crowd.globalfishingwatch.org/api/project/2'/>", "<link rel='parent' title='task' href='http://crowd.globalfishingwatch.org/api/task/4059'/>"], "task_id": 4059, "created": "2016-03-02T19:02:32.376626", "finish_time": "2016-03-02T19:34:26.753038", "calibration": null, "user_ip": null, "link": "<link rel='self' title='taskrun' href='http://crowd.globalfishingwatch.org/api/taskrun/2571'/>", "timeout": null, "project_id": 2, "id": 2571}, {"info": "{\"mmsi\":\"227503000\",\"vesselType\":\"purse_seine\",\"search\":\"Yes\",\"search_url\":\"http://ec.europa.eu/fisheries/fleet/index.cfm?method=Search.DetailSearchSimple&event_key=28297041&search_type=advanced&search_id=2633\"}", "user_id": 13, "links": ["<link rel='parent' title='project' href='http://crowd.globalfishingwatch.org/api/project/2'/>", "<link rel='parent' title='task' href='http://crowd.globalfishingwatch.org/api/task/4059'/>"], "task_id": 4059, "created": "2016-03-08T01:17:32.128431", "finish_time": "2016-03-08T01:18:24.869180", "calibration": null, "user_ip": null, "link": "<link rel='self' title='taskrun' href='http://crowd.globalfishingwatch.org/api/taskrun/2704'/>", "timeout": null, "project_id": 2, "id": 2704}, {"info": "{\"mmsi\":\"227503000\",\"vesselType\":\"purse_seine\",\"search\":\"Yes\",\"search_url\":\"\"}", "user_id": 16, "links": ["<link rel='parent' title='project' href='http://crowd.globalfishingwatch.org/api/project/2'/>", "<link rel='parent' title='task' href='http://crowd.globalfishingwatch.org/api/task/4059'/>"], "task_id": 4059, "created": "2016-03-08T02:08:28.770549", "finish_time": "2016-03-08T02:12:31.811061", "calibration": null, "user_ip": null, "link": "<link rel='self' title='taskrun' href='http://crowd.globalfishingwatch.org/api/taskrun/2740'/>", "timeout": null, "project_id": 2, "id": 2740}]